{"is_source_file": false, "format": "", "description": "", "external_files": [], "external_methods": [], "published": [], "classes": [], "methods": [], "calls": [], "search-terms": [], "state": 2, "file_id": 1, "knowledge_revision": 121, "git_revision": "1b2486fbcf377f0ebc17b7da1fd057e9c578d6d1", "hash": "de5071d2a99e5fb955c5b7b58163bf0e", "format-version": 4, "code-base-name": "main_frontend_app", "filename": "README.md", "revision_history": [{"121": "1b2486fbcf377f0ebc17b7da1fd057e9c578d6d1"}]}